ThinkPython2eZhongwenban/README.md
ThinkPython2eZhongwenban/__init__.py
ThinkPython2eZhongwenban/__main__.py
ThinkPython2eZhongwenban/file.epub
ThinkPython2eZhongwenban/index.html
ThinkPython2eZhongwenban/css/__init__.py
ThinkPython2eZhongwenban/css/annotations.css
ThinkPython2eZhongwenban/css/main.css
ThinkPython2eZhongwenban/css/normalize.css
ThinkPython2eZhongwenban/css/popup.css
ThinkPython2eZhongwenban/font/__init__.py
ThinkPython2eZhongwenban/font/fontello.eot
ThinkPython2eZhongwenban/font/fontello.svg
ThinkPython2eZhongwenban/font/fontello.ttf
ThinkPython2eZhongwenban/font/fontello.woff
ThinkPython2eZhongwenban/img/__init__.py
ThinkPython2eZhongwenban/img/annotator-glyph-sprite.png
ThinkPython2eZhongwenban/img/annotator-icon-sprite.png
ThinkPython2eZhongwenban/img/apple-touch-icon.png
ThinkPython2eZhongwenban/img/cancelfullscreen.png
ThinkPython2eZhongwenban/img/close.png
ThinkPython2eZhongwenban/img/fullscreen.png
ThinkPython2eZhongwenban/img/loader.gif
ThinkPython2eZhongwenban/img/menu-icon.png
ThinkPython2eZhongwenban/img/save.png
ThinkPython2eZhongwenban/img/saved.png
ThinkPython2eZhongwenban/img/settings-s.png
ThinkPython2eZhongwenban/img/settings.png
ThinkPython2eZhongwenban/img/star.png
ThinkPython2eZhongwenban/js/__init__.py
ThinkPython2eZhongwenban/js/epub.js
ThinkPython2eZhongwenban/js/epub.min.js
ThinkPython2eZhongwenban/js/epub.min.map
ThinkPython2eZhongwenban/js/hooks.min.js
ThinkPython2eZhongwenban/js/hooks.min.map
ThinkPython2eZhongwenban/js/reader.js
ThinkPython2eZhongwenban/js/reader.js.map
ThinkPython2eZhongwenban/js/reader.min.js
ThinkPython2eZhongwenban/js/reader.min.map
ThinkPython2eZhongwenban/js/hooks/__init__.py
ThinkPython2eZhongwenban/js/hooks/extensions/__init__.py
ThinkPython2eZhongwenban/js/hooks/extensions/highlight.js
ThinkPython2eZhongwenban/js/libs/__init__.py
ThinkPython2eZhongwenban/js/libs/jquery.min.js
ThinkPython2eZhongwenban/js/libs/localforage.min.js
ThinkPython2eZhongwenban/js/libs/screenfull.js
think_python_2e_zhongwenban-2024.3.2.0.dist-info/METADATA
think_python_2e_zhongwenban-2024.3.2.0.dist-info/WHEEL
think_python_2e_zhongwenban-2024.3.2.0.dist-info/entry_points.txt
think_python_2e_zhongwenban-2024.3.2.0.dist-info/top_level.txt
think_python_2e_zhongwenban-2024.3.2.0.dist-info/RECORD
